url2env/__init__.py
url2env-1.1.dist-info/DESCRIPTION.rst
url2env-1.1.dist-info/METADATA
url2env-1.1.dist-info/RECORD
url2env-1.1.dist-info/WHEEL
url2env-1.1.dist-info/entry_points.txt
url2env-1.1.dist-info/metadata.json
url2env-1.1.dist-info/top_level.txt
