Metadata-Version: 2.0
Name: url2env
Version: 1.1
Summary: Produces env vars from Heroku-style database URLs
Home-page: https://github.com/harto/url2env
Author: Stuart Campbell
Author-email: stuart@harto.org
License: MIT
Keywords: heroku postgresql shell
Platform: UNKNOWN
